nmk_workspace/__init__.py
nmk_workspace/builders.py
nmk_workspace/plugin.yml
nmk_workspace/resolvers.py
nmk_workspace/subprojects.yml
nmk_workspace-1.2.1.dist-info/licenses/LICENSE
nmk_workspace-1.2.1.dist-info/METADATA
nmk_workspace-1.2.1.dist-info/WHEEL
nmk_workspace-1.2.1.dist-info/top_level.txt
nmk_workspace-1.2.1.dist-info/RECORD
