Metadata-Version: 2.4
Name: nmk-workspace
Version: 1.2.1
Summary: VWorkspace handling plugin for nmk build system
Author: The dynod project
Maintainer: The dynod project
License: MIT License
Project-URL: Homepage, https://github.com/dynod/nmk-workspace
Project-URL: Repository, https://github.com/dynod/nmk-workspace
Project-URL: Issues, https://github.com/dynod/nmk/issues?q=is%3Aopen+is%3Aissue+label%3Aplugin%3Aworkspace
Classifier: Programming Language :: Python :: 3.10
Classifier: Programming Language :: Python :: 3.11
Classifier: Programming Language :: Python :: 3.12
Classifier: Programming Language :: Python :: 3.13
Classifier: Programming Language :: Python :: 3.14
Requires-Python: >=3.10
License-File: LICENSE
Requires-Dist: nmk-base
Dynamic: license-file
